uinauil.py
uinauil-1.0.2.dist-info/LICENSE
uinauil-1.0.2.dist-info/METADATA
uinauil-1.0.2.dist-info/WHEEL
uinauil-1.0.2.dist-info/top_level.txt
uinauil-1.0.2.dist-info/RECORD
