Metadata-Version: 2.1
Name: uinauil
Version: 1.0.2
Summary: Download language resources in Italian from ELG
Author: Valerio Basile, Alessio Bosca, Livio Bioglio
License: GNU GENERAL PUBLIC LICENSE
Project-URL: Homepage, https://github.com/valeriobasile/uinauil
Keywords: Language resources,Italian language,NLP,Natural Language Processing,ELG
Classifier: Development Status :: 4 - Beta
Classifier: Intended Audience :: Science/Research
Classifier: License :: OSI Approved :: GNU General Public License v3 or later (GPLv3+)
Classifier: Natural Language :: Italian
Classifier: Programming Language :: Python
Classifier: Programming Language :: Python :: 3
Classifier: Topic :: Scientific/Engineering :: Artificial Intelligence
Classifier: Topic :: Scientific/Engineering :: Information Analysis
Requires-Python: >=3.6.7
License-File: LICENSE
Requires-Dist: elg ==0.3.6
Requires-Dist: scikit-learn >=1.2.1
